workspace_services/__init__.py
workspace_services/_info.py
workspace_services/batch.py
workspace_services/memory_manager.py
workspace_services/py.typed
workspace_services/settings.py
workspace_services/task.py
workspace_services/workspace.py
workspace_services/tag_models/classification_tag.py
workspace_services/tag_models/detection_tag.py
workspace_services/tag_models/tag_base.py
workspace_services-0.0.14.dist-info/METADATA
workspace_services-0.0.14.dist-info/WHEEL
workspace_services-0.0.14.dist-info/top_level.txt
workspace_services-0.0.14.dist-info/RECORD
