Metadata-Version: 2.4
Name: workspace_services
Version: 0.0.14
Summary: Workspace Services
Author-email: Sheldon Lee <sheldonlee@outlook.com>
Classifier: Programming Language :: Python :: 3
Classifier: Operating System :: OS Independent
Requires-Python: >=3.12
Requires-Dist: rich
Requires-Dist: scikit-learn
Provides-Extra: dev
Requires-Dist: build; extra == "dev"
Requires-Dist: pytest; extra == "dev"
Requires-Dist: pytest-env; extra == "dev"
Requires-Dist: mypy; extra == "dev"
Requires-Dist: pre-commit; extra == "dev"
